netproxy/__init__.py
netproxy/__main__.py
netproxy/_re.py
netproxy/config.py
netproxy/constants.py
netproxy/context.py
netproxy/utils.py
netproxy/components/__init__.py
netproxy/components/http_proxy.py
netproxy/components/listeners.py
netproxy/components/reverse_proxy.py
netproxy/components/rules.py
netproxy/components/sslcontext.py
netproxy/models/__init__.py
netproxy/models/_utils.py
netproxy/models/config.py
netproxy-0.2.1.dist-info/METADATA
netproxy-0.2.1.dist-info/WHEEL
netproxy-0.2.1.dist-info/top_level.txt
netproxy-0.2.1.dist-info/RECORD
